README.md
setup.py
bin/mdf_pyro_server.py
bin/mdf_viewer.py
mdf/__init__.py
mdf/common.py
mdf/context.py
mdf/cqueue.py
mdf/ctx_pickle.py
mdf/nodes.py
mdf/nodetypes.py
mdf/parser.py
mdf/runner.py
mdf/to_dot.py
mdf.egg-info/PKG-INFO
mdf.egg-info/SOURCES.txt
mdf.egg-info/dependency_links.txt
mdf.egg-info/not-zip-safe
mdf.egg-info/requires.txt
mdf.egg-info/top_level.txt
mdf/builders/__init__.py
mdf/builders/basic.py
mdf/io/__init__.py
mdf/io/simplezipfile.py
mdf/lab/__init__.py
mdf/lab/progress.py
mdf/regression/__init__.py
mdf/regression/differs.py
mdf/remote/__init__.py
mdf/remote/messaging.py
mdf/remote/serializer.py
mdf/tests/__init__.py
mdf/tests/test_basic.py
mdf/tests/test_cls_nodes.py
mdf/tests/test_conditional_dependecies.py
mdf/tests/test_context.py
mdf/tests/test_exceptions.py
mdf/tests/test_filtering.py
mdf/tests/test_nodes.py
mdf/tests/test_nodes_ext.py
mdf/tests/test_override.py
mdf/tests/test_parser.py
mdf/tests/test_pickle.py
mdf/tests/test_regression.py
mdf/tests/test_remote.py
mdf/viewer/__init__.py
mdf/viewer/common.py
mdf/viewer/dialogs.py
mdf/viewer/excel.py
mdf/viewer/frame.py
mdf/viewer/mixins.py
mdf/viewer/icons/__init__.py
mdf/viewer/icons/filter.ico
mdf/viewer/icons/frame.ico
mdf/viewer/icons/run.ico
mdf/viewer/icons/step.ico
mdf/viewer/panels/__init__.py
mdf/viewer/panels/codeviewer.py
mdf/viewer/panels/dagviewer.py
mdf/viewer/panels/plotpanel.py
mdf/viewer/panels/propspanel.py
mdf/viewer/panels/valueviewer.py