Metadata-Version: 2.1
Name: mdf
Version: 2.2.1
Summary: MDF - Data Flow Programming Toolkit
Home-page: UNKNOWN
License: UNKNOWN
Platform: UNKNOWN
Provides-Extra: linux2
Provides-Extra: win32
